README.md
setup.cfg
setup.py
inliner/__init__.py
inliner/common.py
inliner/contexts.py
inliner/inliner.py
inliner/interactive.py
inliner/targets.py
inliner/tracer.py
inliner/transforms.py
inliner.egg-info/PKG-INFO
inliner.egg-info/SOURCES.txt
inliner.egg-info/dependency_links.txt
inliner.egg-info/not-zip-safe
inliner.egg-info/requires.txt
inliner.egg-info/top_level.txt
inliner/passes/__init__.py
inliner/passes/base_pass.py
inliner/passes/clean_imports.py
inliner/passes/copy_propagation.py
inliner/passes/deadcode.py
inliner/passes/inline.py
inliner/passes/record_to_vars.py
inliner/passes/remove_suffixes.py
inliner/passes/unused_vars.py
inliner/visitors/__init__.py
inliner/visitors/imports.py
inliner/visitors/insert_statements.py
inliner/visitors/is_pure.py
inliner/visitors/libcst_dropin.py
inliner/visitors/rename.py
inliner/visitors/replacers.py
inliner_jupyter/inliner.json
inliner_jupyter/dist/notebook.js
inliner_jupyter/dist/notebook.js.map