Metadata-Version: 1.0
Name: inliner
Version: 0.4.1
Summary: Human-readable inlining of Python code
Home-page: http://github.com/willcrichton/inliner
Author: Will Crichton
Author-email: wcrichto@cs.stanford.edu
License: Apache 2.0
Platform: UNKNOWN
